NoobNote/README.txt
NoobNote/__init__.py
NoobNote/__main__.py
NoobNote/icon.ico
NoobNote/leaf.py
NoobNote-1.2.2.dist-info/LICENSE
NoobNote-1.2.2.dist-info/METADATA
NoobNote-1.2.2.dist-info/WHEEL
NoobNote-1.2.2.dist-info/entry_points.txt
NoobNote-1.2.2.dist-info/top_level.txt
NoobNote-1.2.2.dist-info/RECORD
