Metadata-Version: 2.1
Name: NoobNote
Version: 1.2.2
Summary: A Simple Notepad
Home-page: https://newtoallofthis123.github.io/NoobNote
Author: NoobScience
Author-email: noobscience123@gmail.com
License: MIT
Project-URL: Author WebSite, https://newtoallofthis123.github.io/About
Project-URL: Bug Tracker, https://github.com/newtoallofthis123/NoobNote/issues
Platform: UNKNOWN
Classifier: License :: OSI Approved :: MIT License
Classifier: Programming Language :: Python :: 3
Classifier: Programming Language :: Python :: 3.7
Requires-Python: >=3.6
License-File: LICENSE
Requires-Dist: PyQRCode
Requires-Dist: pypng
Requires-Dist: rich
